tests/__init__.py
tests/library/__init__.py
tests/library/nlp_library_tests.py
tests/library/resources/__init__.py
tests/preprocess/__init__.py
tests/preprocess/text_preprocess_tests.py
txplib-0.1.dist-info/LICENSE
txplib-0.1.dist-info/METADATA
txplib-0.1.dist-info/WHEEL
txplib-0.1.dist-info/top_level.txt
txplib-0.1.dist-info/zip-safe
txplib-0.1.dist-info/RECORD
