Metadata-Version: 2.1
Name: txplib
Version: 0.1
Summary: text preprocessing utils.
Home-page: https://github.com/KeyiT/txplib
Author: keyi.tang
Author-email: keyit92@gmail.com
License: UNKNOWN
Platform: UNKNOWN
Classifier: Programming Language :: Python :: 3
Classifier: License :: OSI Approved :: MIT License
Classifier: Operating System :: OS Independent
Requires-Dist: numpy (==1.14.5)
Requires-Dist: nltk (==3.3)
Requires-Dist: scipy (==1.1.0)
